title_checker/__init__.py
title_checker/title_checker.py
title_checker-0.9.data/scripts/title_checker
title_checker-0.9.dist-info/METADATA
title_checker-0.9.dist-info/WHEEL
title_checker-0.9.dist-info/top_level.txt
title_checker-0.9.dist-info/RECORD
