Metadata-Version: 2.1
Name: title-checker
Version: 0.9
Summary: A Python script for checking the titles of each youtube links in a text file
Home-page: https://github.com/MojtabaMonfared/title_checker
Author: Mojtaba Monfared
Author-email: 4lientears@gmail.com
Classifier: Programming Language :: Python :: 3
Classifier: Operating System :: OS Independent
Requires-Dist: selenium
Requires-Dist: typer
Requires-Dist: questionary
